<?xml version="1.0" encoding="UTF-8"?>
<endringssett xmlns="http://nvdb.vegvesen.no/apiskriv/domain/v2" effektDato="2015-11-05" datakatalogversjon="2.01">
	<registrer>
		<vegObjekter>
			<vegObjekt typeId="761" tempId="-557">
				<egenskaper>
					<egenskap typeId="7596">
						<verdi>Tiltaksbehov</verdi>
					</egenskap>
					<egenskap typeId="7859">
						<verdi>for liten</verdi>
					</egenskap>
					<egenskap typeId="7594">
						<verdi>Skiftes</verdi>
					</egenskap>
				</egenskaper>
				<lokasjon>
					<punkt lenkeId="1023732" posisjon="0.71514326576986209"/>
				</lokasjon>
			</vegObjekt>
			<vegObjekt typeId="761" tempId="-559">
				<egenskaper>
					<egenskap typeId="7596">
						<verdi>Tiltaksbehov</verdi>
					</egenskap>
					<egenskap typeId="7859">
						<verdi>for liten</verdi>
					</egenskap>
					<egenskap typeId="7594">
						<verdi>Skiftes</verdi>
					</egenskap>
				</egenskaper>
				<lokasjon>
					<punkt lenkeId="1023732" posisjon="0.68136978827129757"/>
				</lokasjon>
			</vegObjekt>
			<vegObjekt typeId="761" tempId="-561">
				<egenskaper>
					<egenskap typeId="7596">
						<verdi>Ok</verdi>
					</egenskap>
					<egenskap typeId="7859">
						<verdi>for liten</verdi>
					</egenskap>
					<egenskap typeId="7594">
						<verdi>Ryddes</verdi>
					</egenskap>
				</egenskaper>
				<lokasjon>
					<punkt lenkeId="1023732" posisjon="0.42231682965070255"/>
				</lokasjon>
			</vegObjekt>
			<vegObjekt typeId="761" tempId="-563">
				<egenskaper>
					<egenskap typeId="7596">
						<verdi>Ok</verdi>
					</egenskap>
					<egenskap typeId="7859">
						<verdi>for liten</verdi>
					</egenskap>
					<egenskap typeId="7594">
						<verdi>Ryddes</verdi>
					</egenskap>
				</egenskaper>
				<lokasjon>
					<punkt lenkeId="1023732" posisjon="0.26795304790166574"/>
				</lokasjon>
			</vegObjekt>
			<vegObjekt typeId="761" tempId="-565">
				<egenskaper>
					<egenskap typeId="7596">
						<verdi>Ok</verdi>
					</egenskap>
					<egenskap typeId="7594">
						<verdi>Ryddes</verdi>
					</egenskap>
				</egenskaper>
				<lokasjon>
					<punkt lenkeId="1025626" posisjon="0.18493492342052731"/>
				</lokasjon>
			</vegObjekt>
			<vegObjekt typeId="79" tempId="-556">
				<egenskaper>
					<egenskap typeId="1941">
						<verdi>Nei</verdi>
					</egenskap>
					<egenskap typeId="6981">
						<verdi>Vann</verdi>
					</egenskap>
					<egenskap typeId="7996">
						<verdi>Privat</verdi>
					</egenskap>
					<egenskap typeId="1923">
						<verdi>Nei</verdi>
					</egenskap>
					<egenskap typeId="4548">
						<verdi>100</verdi>
					</egenskap>
					<egenskap typeId="10223">
						<verdi>Nei</verdi>
					</egenskap>
					<egenskap typeId="6984">
						<verdi>Sirkulær</verdi>
					</egenskap>
					<egenskap typeId="6983">
						<verdi>Plast</verdi>
					</egenskap>
					<egenskap typeId="1939">
						<verdi>Åpent i grøft</verdi>
					</egenskap>
					<egenskap typeId="1940">
						<verdi>I skråning/terreng</verdi>
					</egenskap>
					<egenskap typeId="4562">
						<verdi>Masser, innløp</verdi>
					</egenskap>
					<egenskap typeId="4549">
						<verdi>100</verdi>
					</egenskap>
					<egenskap typeId="5899">
						<verdi>målemetode=96; nøyaktighet=10; synbarhet=1; målemetodeHøyde=96; nøyaktighetHøyde=10; LINESTRING (247812.644519273 6816910.41545377,247805.410772744 6816912.22437361)</verdi>
					</egenskap>
				</egenskaper>
				<assosiasjoner>
					<assosiasjon typeId="221093">
						<tempId>-557</tempId>
					</assosiasjon>
				</assosiasjoner>
				<lokasjon>
					<punkt lenkeId="1023732" posisjon="0.71514326576986209"/>
				</lokasjon>
			</vegObjekt>
			<vegObjekt typeId="79" tempId="-558">
				<egenskaper>
					<egenskap typeId="1941">
						<verdi>Nei</verdi>
					</egenskap>
					<egenskap typeId="6981">
						<verdi>Vann</verdi>
					</egenskap>
					<egenskap typeId="7996">
						<verdi>Privat</verdi>
					</egenskap>
					<egenskap typeId="1923">
						<verdi>Nei</verdi>
					</egenskap>
					<egenskap typeId="4548">
						<verdi>100</verdi>
					</egenskap>
					<egenskap typeId="10223">
						<verdi>Nei</verdi>
					</egenskap>
					<egenskap typeId="6984">
						<verdi>Sirkulær</verdi>
					</egenskap>
					<egenskap typeId="6983">
						<verdi>Plast</verdi>
					</egenskap>
					<egenskap typeId="1939">
						<verdi>Åpent i grøft</verdi>
					</egenskap>
					<egenskap typeId="1940">
						<verdi>I skråning/terreng</verdi>
					</egenskap>
					<egenskap typeId="4562">
						<verdi>Masser, innløp</verdi>
					</egenskap>
					<egenskap typeId="4549">
						<verdi>100</verdi>
					</egenskap>
					<egenskap typeId="5899">
						<verdi>målemetode=96; nøyaktighet=10; synbarhet=1; målemetodeHøyde=96; nøyaktighetHøyde=10; LINESTRING (247819.826905865 6816938.71820193,247813.03687147 6816941.03390271)</verdi>
					</egenskap>
				</egenskaper>
				<assosiasjoner>
					<assosiasjon typeId="221093">
						<tempId>-559</tempId>
					</assosiasjon>
				</assosiasjoner>
				<lokasjon>
					<punkt lenkeId="1023732" posisjon="0.68136978827129757"/>
				</lokasjon>
			</vegObjekt>
			<vegObjekt typeId="79" tempId="-560">
				<egenskaper>
					<egenskap typeId="1941">
						<verdi>Nei</verdi>
					</egenskap>
					<egenskap typeId="6981">
						<verdi>Vann</verdi>
					</egenskap>
					<egenskap typeId="7996">
						<verdi>Privat</verdi>
					</egenskap>
					<egenskap typeId="1923">
						<verdi>Nei</verdi>
					</egenskap>
					<egenskap typeId="4548">
						<verdi>300</verdi>
					</egenskap>
					<egenskap typeId="10223">
						<verdi>Ja</verdi>
					</egenskap>
					<egenskap typeId="6984">
						<verdi>Sirkulær</verdi>
					</egenskap>
					<egenskap typeId="6983">
						<verdi>Plast</verdi>
					</egenskap>
					<egenskap typeId="1939">
						<verdi>Åpent i grøft</verdi>
					</egenskap>
					<egenskap typeId="1940">
						<verdi>I bekk/elv</verdi>
					</egenskap>
					<egenskap typeId="4562">
						<verdi>Masser, innløp</verdi>
					</egenskap>
					<egenskap typeId="4549">
						<verdi>300</verdi>
					</egenskap>
					<egenskap typeId="5899">
						<verdi>målemetode=96; nøyaktighet=10; synbarhet=1; målemetodeHøyde=96; nøyaktighetHøyde=10; LINESTRING (247826.230879769 6817164.59776619,247819.916438138 6817161.80656116)</verdi>
					</egenskap>
				</egenskaper>
				<assosiasjoner>
					<assosiasjon typeId="221093">
						<tempId>-561</tempId>
					</assosiasjon>
				</assosiasjoner>
				<lokasjon>
					<punkt lenkeId="1023732" posisjon="0.42231682965070255"/>
				</lokasjon>
			</vegObjekt>
			<vegObjekt typeId="79" tempId="-562">
				<egenskaper>
					<egenskap typeId="1941">
						<verdi>Nei</verdi>
					</egenskap>
					<egenskap typeId="6981">
						<verdi>Vann</verdi>
					</egenskap>
					<egenskap typeId="7996">
						<verdi>Privat</verdi>
					</egenskap>
					<egenskap typeId="1923">
						<verdi>Nei</verdi>
					</egenskap>
					<egenskap typeId="4548">
						<verdi>400</verdi>
					</egenskap>
					<egenskap typeId="10223">
						<verdi>Ja</verdi>
					</egenskap>
					<egenskap typeId="6984">
						<verdi>Sirkulær</verdi>
					</egenskap>
					<egenskap typeId="6983">
						<verdi>Plast</verdi>
					</egenskap>
					<egenskap typeId="1939">
						<verdi>Åpent i grøft</verdi>
					</egenskap>
					<egenskap typeId="1940">
						<verdi>I bekk/elv</verdi>
					</egenskap>
					<egenskap typeId="4562">
						<verdi>Masser, innløp</verdi>
					</egenskap>
					<egenskap typeId="4549">
						<verdi>400</verdi>
					</egenskap>
					<egenskap typeId="5899">
						<verdi>målemetode=96; nøyaktighet=10; synbarhet=1; målemetodeHøyde=96; nøyaktighetHøyde=10; LINESTRING (247800.721409059 6817291.44882876,247796.795436423 6817286.57307638)</verdi>
					</egenskap>
				</egenskaper>
				<assosiasjoner>
					<assosiasjon typeId="221093">
						<tempId>-563</tempId>
					</assosiasjon>
				</assosiasjoner>
				<lokasjon>
					<punkt lenkeId="1023732" posisjon="0.26795304790166574"/>
				</lokasjon>
			</vegObjekt>
			<vegObjekt typeId="79" tempId="-564">
				<egenskaper>
					<egenskap typeId="1941">
						<verdi>Nei</verdi>
					</egenskap>
					<egenskap typeId="6981">
						<verdi>Vann</verdi>
					</egenskap>
					<egenskap typeId="7996">
						<verdi>Privat</verdi>
					</egenskap>
					<egenskap typeId="1923">
						<verdi>Nei</verdi>
					</egenskap>
					<egenskap typeId="4548">
						<verdi>150</verdi>
					</egenskap>
					<egenskap typeId="10223">
						<verdi>Nei</verdi>
					</egenskap>
					<egenskap typeId="6984">
						<verdi>Sirkulær</verdi>
					</egenskap>
					<egenskap typeId="6983">
						<verdi>Betong</verdi>
					</egenskap>
					<egenskap typeId="1939">
						<verdi>Åpent i grøft</verdi>
					</egenskap>
					<egenskap typeId="1940">
						<verdi>I skråning/terreng</verdi>
					</egenskap>
					<egenskap typeId="4562">
						<verdi>Masser, innløp</verdi>
					</egenskap>
					<egenskap typeId="4549">
						<verdi>150</verdi>
					</egenskap>
					<egenskap typeId="5899">
						<verdi>målemetode=96; nøyaktighet=10; synbarhet=1; målemetodeHøyde=96; nøyaktighetHøyde=10; LINESTRING (247561.784758176 6817467.95358102,247562.055254662 6817462.12691431)</verdi>
					</egenskap>
				</egenskaper>
				<assosiasjoner>
					<assosiasjon typeId="221093">
						<tempId>-565</tempId>
					</assosiasjon>
				</assosiasjoner>
				<lokasjon>
					<punkt lenkeId="1025626" posisjon="0.18493492342052731"/>
				</lokasjon>
			</vegObjekt>
		</vegObjekter>
	</registrer>
</endringssett>
