<?xml version="1.0" encoding="UTF-8"?>
<endringssett xmlns="http://nvdb.vegvesen.no/apiskriv/domain/v2" effektDato="2016-02-10" datakatalogversjon="2.04">
	<registrer>
		<vegObjekter>
			<vegObjekt typeId="79" tempId="-398">
				<egenskaper>
					<egenskap typeId="4549">
						<verdi>450</verdi>
					</egenskap>
					<egenskap typeId="6984">
						<verdi>Rektangulær</verdi>
					</egenskap>
					<egenskap typeId="6981">
						<verdi>Vann</verdi>
					</egenskap>
					<egenskap typeId="6983">
						<verdi>Naturstein</verdi>
					</egenskap>
					<egenskap typeId="1923">
						<verdi>Nei</verdi>
					</egenskap>
					<egenskap typeId="1939">
						<verdi>Åpent med frontmur</verdi>
					</egenskap>
					<egenskap typeId="1940">
						<verdi>I skråning/terreng</verdi>
					</egenskap>
					<egenskap typeId="4548">
						<verdi>500</verdi>
					</egenskap>
					<egenskap typeId="7996">
						<verdi>Privat</verdi>
					</egenskap>
					<egenskap typeId="4562">
						<verdi>Masser, innløp</verdi>
					</egenskap>
					<egenskap typeId="5899">
						<verdi>målemetode=96; nøyaktighet=10; nøyaktighetHøyde=10; LINESTRING(243306.39533968447 6830809.8089431357 460.801,243301.41689081851 6830806.3963819109 459.367)</verdi>
					</egenskap>
				</egenskaper>
				<lokasjon>
					<punkt lenkeId="1025179" posisjon="0.74337113343168182"/>
				</lokasjon>
			</vegObjekt>
			<vegObjekt typeId="79" tempId="-399">
				<egenskaper>
					<egenskap typeId="4549">
						<verdi>200</verdi>
					</egenskap>
					<egenskap typeId="6984">
						<verdi>Sirkulær</verdi>
					</egenskap>
					<egenskap typeId="6981">
						<verdi>Vann</verdi>
					</egenskap>
					<egenskap typeId="6983">
						<verdi>Plast</verdi>
					</egenskap>
					<egenskap typeId="1923">
						<verdi>Nei</verdi>
					</egenskap>
					<egenskap typeId="1939">
						<verdi>Åpent i grøft</verdi>
					</egenskap>
					<egenskap typeId="1940">
						<verdi>I skråning/terreng</verdi>
					</egenskap>
					<egenskap typeId="4548">
						<verdi>200</verdi>
					</egenskap>
					<egenskap typeId="7996">
						<verdi>Privat</verdi>
					</egenskap>
					<egenskap typeId="4562">
						<verdi>Masser, innløp</verdi>
					</egenskap>
					<egenskap typeId="5899">
						<verdi>målemetode=96; nøyaktighet=10; nøyaktighetHøyde=10; LINESTRING(243438.80476848118 6830648.5785771329 490.226,243434.13419302079 6830652.8199366629 489.542)</verdi>
					</egenskap>
				</egenskaper>
				<lokasjon>
					<punkt lenkeId="1024234" posisjon="0.50552882521922793"/>
				</lokasjon>
			</vegObjekt>
		</vegObjekter>
	</registrer>
</endringssett>
