<?xml version="1.0" encoding="UTF-8"?>
<endringssett xmlns="http://nvdb.vegvesen.no/apiskriv/domain/v2" effektDato="2016-02-10" datakatalogversjon="2.04">
	<registrer>
		<vegObjekter>
			<vegObjekt typeId="761" tempId="-1245">
				<egenskaper>
					<egenskap typeId="7596">
						<verdi>Funksjonell</verdi>
					</egenskap>
					<egenskap typeId="7594">
						<verdi>Utbedres på stedet</verdi>
					</egenskap>
				</egenskaper>
				<lokasjon>
					<punkt lenkeId="1003412" posisjon="0.0017151909003174652"/>
				</lokasjon>
			</vegObjekt>
			<vegObjekt typeId="761" tempId="-1247">
				<egenskaper>
					<egenskap typeId="7596">
						<verdi>Ok</verdi>
					</egenskap>
					<egenskap typeId="7594">
						<verdi>Ryddes</verdi>
					</egenskap>
				</egenskaper>
				<lokasjon>
					<punkt lenkeId="1003412" posisjon="0.036775790393200905"/>
				</lokasjon>
			</vegObjekt>
			<vegObjekt typeId="761" tempId="-1249">
				<egenskaper>
					<egenskap typeId="7596">
						<verdi>Ok</verdi>
					</egenskap>
					<egenskap typeId="7594">
						<verdi>Ryddes</verdi>
					</egenskap>
				</egenskaper>
				<lokasjon>
					<punkt lenkeId="1023877" posisjon="0.084087212091194491"/>
				</lokasjon>
			</vegObjekt>
			<vegObjekt typeId="761" tempId="-1251">
				<egenskaper>
					<egenskap typeId="7596">
						<verdi>Ok</verdi>
					</egenskap>
					<egenskap typeId="7594">
						<verdi>Ryddes</verdi>
					</egenskap>
				</egenskaper>
				<lokasjon>
					<punkt lenkeId="1003412" posisjon="0.13843818419767129"/>
				</lokasjon>
			</vegObjekt>
			<vegObjekt typeId="761" tempId="-1253">
				<egenskaper>
					<egenskap typeId="7596">
						<verdi>Funksjonell</verdi>
					</egenskap>
					<egenskap typeId="7859">
						<verdi>kanskje klemt</verdi>
					</egenskap>
					<egenskap typeId="7594">
						<verdi>Utbedres på stedet</verdi>
					</egenskap>
				</egenskaper>
				<lokasjon>
					<punkt lenkeId="1003412" posisjon="0.1940763602150124"/>
				</lokasjon>
			</vegObjekt>
			<vegObjekt typeId="761" tempId="-1255">
				<egenskaper>
					<egenskap typeId="7596">
						<verdi>Tiltaksbehov</verdi>
					</egenskap>
					<egenskap typeId="7594">
						<verdi>Skiftes</verdi>
					</egenskap>
				</egenskaper>
				<lokasjon>
					<punkt lenkeId="1003412" posisjon="0.27279477000209285"/>
				</lokasjon>
			</vegObjekt>
			<vegObjekt typeId="761" tempId="-1257">
				<egenskaper>
					<egenskap typeId="7596">
						<verdi>Tiltaksbehov</verdi>
					</egenskap>
					<egenskap typeId="7859">
						<verdi>helt tett</verdi>
					</egenskap>
					<egenskap typeId="7594">
						<verdi>Skiftes</verdi>
					</egenskap>
				</egenskaper>
				<lokasjon>
					<punkt lenkeId="1003412" posisjon="0.31985249853277875"/>
				</lokasjon>
			</vegObjekt>
			<vegObjekt typeId="761" tempId="-1259">
				<egenskaper>
					<egenskap typeId="7596">
						<verdi>Tiltaksbehov</verdi>
					</egenskap>
					<egenskap typeId="7594">
						<verdi>Skiftes</verdi>
					</egenskap>
				</egenskaper>
				<lokasjon>
					<punkt lenkeId="1003412" posisjon="0.37165540936279845"/>
				</lokasjon>
			</vegObjekt>
			<vegObjekt typeId="761" tempId="-1261">
				<egenskaper>
					<egenskap typeId="7596">
						<verdi>Tiltaksbehov</verdi>
					</egenskap>
					<egenskap typeId="7859">
						<verdi>helt tett</verdi>
					</egenskap>
					<egenskap typeId="7594">
						<verdi>Skiftes</verdi>
					</egenskap>
				</egenskaper>
				<lokasjon>
					<punkt lenkeId="1003412" posisjon="0.4118189537411609"/>
				</lokasjon>
			</vegObjekt>
			<vegObjekt typeId="79" tempId="-1244">
				<egenskaper>
					<egenskap typeId="10223">
						<verdi>Nei</verdi>
					</egenskap>
					<egenskap typeId="6981">
						<verdi>Vann</verdi>
					</egenskap>
					<egenskap typeId="4549">
						<verdi>500</verdi>
					</egenskap>
					<egenskap typeId="7996">
						<verdi>Kommune</verdi>
					</egenskap>
					<egenskap typeId="4548">
						<verdi>500</verdi>
					</egenskap>
					<egenskap typeId="1941">
						<verdi>Nei</verdi>
					</egenskap>
					<egenskap typeId="6984">
						<verdi>Sirkulær</verdi>
					</egenskap>
					<egenskap typeId="1923">
						<verdi>Nei</verdi>
					</egenskap>
					<egenskap typeId="4562">
						<verdi>Masser, utløp</verdi>
					</egenskap>
					<egenskap typeId="6983">
						<verdi>Betong</verdi>
					</egenskap>
					<egenskap typeId="1939">
						<verdi>Åpent i grøft</verdi>
					</egenskap>
					<egenskap typeId="1940">
						<verdi>Åpen grøft</verdi>
					</egenskap>
					<egenskap typeId="5899">
						<verdi>målemetode=96; nøyaktighet=10; synbarhet=1; målemetodeHøyde=96; nøyaktighetHøyde=10; LINESTRING(246190.4053864512 6815720.9440448936,246184.78960297359 6815712.3478233367)</verdi>
					</egenskap>
				</egenskaper>
				<assosiasjoner>
					<assosiasjon typeId="221093">
						<tempId>-1245</tempId>
					</assosiasjon>
				</assosiasjoner>
				<lokasjon>
					<punkt lenkeId="1003412" posisjon="0.0017151909003174652"/>
				</lokasjon>
			</vegObjekt>
			<vegObjekt typeId="79" tempId="-1246">
				<egenskaper>
					<egenskap typeId="10223">
						<verdi>Nei</verdi>
					</egenskap>
					<egenskap typeId="6981">
						<verdi>Vann</verdi>
					</egenskap>
					<egenskap typeId="4549">
						<verdi>600</verdi>
					</egenskap>
					<egenskap typeId="7996">
						<verdi>Kommune</verdi>
					</egenskap>
					<egenskap typeId="4548">
						<verdi>400</verdi>
					</egenskap>
					<egenskap typeId="1941">
						<verdi>Nei</verdi>
					</egenskap>
					<egenskap typeId="6984">
						<verdi>Rektangulær</verdi>
					</egenskap>
					<egenskap typeId="1923">
						<verdi>Nei</verdi>
					</egenskap>
					<egenskap typeId="4562">
						<verdi>Masser, innløp</verdi>
					</egenskap>
					<egenskap typeId="6983">
						<verdi>Naturstein</verdi>
					</egenskap>
					<egenskap typeId="1939">
						<verdi>Åpent i grøft</verdi>
					</egenskap>
					<egenskap typeId="1940">
						<verdi>Åpen grøft</verdi>
					</egenskap>
					<egenskap typeId="5899">
						<verdi>målemetode=96; nøyaktighet=10; synbarhet=1; målemetodeHøyde=96; nøyaktighetHøyde=10; LINESTRING(246307.75999556368 6815689.5177473063,246304.80282931522 6815683.040035041)</verdi>
					</egenskap>
				</egenskaper>
				<assosiasjoner>
					<assosiasjon typeId="221093">
						<tempId>-1247</tempId>
					</assosiasjon>
				</assosiasjoner>
				<lokasjon>
					<punkt lenkeId="1003412" posisjon="0.036775790393200905"/>
				</lokasjon>
			</vegObjekt>
			<vegObjekt typeId="79" tempId="-1248">
				<egenskaper>
					<egenskap typeId="10223">
						<verdi>Nei</verdi>
					</egenskap>
					<egenskap typeId="6981">
						<verdi>Vann</verdi>
					</egenskap>
					<egenskap typeId="4549">
						<verdi>250</verdi>
					</egenskap>
					<egenskap typeId="7996">
						<verdi>Kommune</verdi>
					</egenskap>
					<egenskap typeId="4548">
						<verdi>250</verdi>
					</egenskap>
					<egenskap typeId="1941">
						<verdi>Nei</verdi>
					</egenskap>
					<egenskap typeId="6984">
						<verdi>Sirkulær</verdi>
					</egenskap>
					<egenskap typeId="1923">
						<verdi>Nei</verdi>
					</egenskap>
					<egenskap typeId="4562">
						<verdi>Masser, innløp</verdi>
					</egenskap>
					<egenskap typeId="6983">
						<verdi>Plast</verdi>
					</egenskap>
					<egenskap typeId="1939">
						<verdi>Åpent i grøft</verdi>
					</egenskap>
					<egenskap typeId="1940">
						<verdi>Åpen grøft</verdi>
					</egenskap>
					<egenskap typeId="5899">
						<verdi>målemetode=96; nøyaktighet=10; synbarhet=1; målemetodeHøyde=96; nøyaktighetHøyde=10; LINESTRING(246302.48569802128 6815682.1613387298,246292.52239471435 6815666.8970696507)</verdi>
					</egenskap>
				</egenskaper>
				<assosiasjoner>
					<assosiasjon typeId="221093">
						<tempId>-1249</tempId>
					</assosiasjon>
				</assosiasjoner>
				<lokasjon>
					<punkt lenkeId="1023877" posisjon="0.084087212091194491"/>
				</lokasjon>
			</vegObjekt>
			<vegObjekt typeId="79" tempId="-1250">
				<egenskaper>
					<egenskap typeId="10223">
						<verdi>Ja</verdi>
					</egenskap>
					<egenskap typeId="6981">
						<verdi>Vann</verdi>
					</egenskap>
					<egenskap typeId="4549">
						<verdi>800</verdi>
					</egenskap>
					<egenskap typeId="7996">
						<verdi>Kommune</verdi>
					</egenskap>
					<egenskap typeId="4548">
						<verdi>800</verdi>
					</egenskap>
					<egenskap typeId="1941">
						<verdi>Nei</verdi>
					</egenskap>
					<egenskap typeId="6984">
						<verdi>Sirkulær</verdi>
					</egenskap>
					<egenskap typeId="1923">
						<verdi>Ja</verdi>
					</egenskap>
					<egenskap typeId="4562">
						<verdi>Masser, innløp</verdi>
					</egenskap>
					<egenskap typeId="6983">
						<verdi>Plast</verdi>
					</egenskap>
					<egenskap typeId="1939">
						<verdi>Åpent med frontmur</verdi>
					</egenskap>
					<egenskap typeId="1940">
						<verdi>I bekk/elv</verdi>
					</egenskap>
					<egenskap typeId="5899">
						<verdi>målemetode=96; nøyaktighet=10; synbarhet=1; målemetodeHøyde=96; nøyaktighetHøyde=10; LINESTRING(246607.06668228214 6815549.6923313336,246593.71533617761 6815542.0739201363)</verdi>
					</egenskap>
				</egenskaper>
				<assosiasjoner>
					<assosiasjon typeId="221093">
						<tempId>-1251</tempId>
					</assosiasjon>
				</assosiasjoner>
				<lokasjon>
					<punkt lenkeId="1003412" posisjon="0.13843818419767129"/>
				</lokasjon>
			</vegObjekt>
			<vegObjekt typeId="79" tempId="-1252">
				<egenskaper>
					<egenskap typeId="1941">
						<verdi>Nei</verdi>
					</egenskap>
					<egenskap typeId="6981">
						<verdi>Vann</verdi>
					</egenskap>
					<egenskap typeId="4548">
						<verdi>300</verdi>
					</egenskap>
					<egenskap typeId="10223">
						<verdi>Nei</verdi>
					</egenskap>
					<egenskap typeId="6984">
						<verdi>Ellipseform</verdi>
					</egenskap>
					<egenskap typeId="1923">
						<verdi>Ja</verdi>
					</egenskap>
					<egenskap typeId="4562">
						<verdi>Masser, innløp</verdi>
					</egenskap>
					<egenskap typeId="7996">
						<verdi>Kommune</verdi>
					</egenskap>
					<egenskap typeId="4549">
						<verdi>200</verdi>
					</egenskap>
					<egenskap typeId="1939">
						<verdi>Åpent i grøft</verdi>
					</egenskap>
					<egenskap typeId="1940">
						<verdi>I skråning/terreng</verdi>
					</egenskap>
					<egenskap typeId="6983">
						<verdi>Plast</verdi>
					</egenskap>
					<egenskap typeId="5899">
						<verdi>målemetode=96; nøyaktighet=10; synbarhet=1; målemetodeHøyde=96; nøyaktighetHøyde=10; LINESTRING(246771.98297279986 6815462.7552407859,246764.05691445858 6815460.7416872084)</verdi>
					</egenskap>
				</egenskaper>
				<assosiasjoner>
					<assosiasjon typeId="221093">
						<tempId>-1253</tempId>
					</assosiasjon>
				</assosiasjoner>
				<lokasjon>
					<punkt lenkeId="1003412" posisjon="0.1940763602150124"/>
				</lokasjon>
			</vegObjekt>
			<vegObjekt typeId="79" tempId="-1254">
				<egenskaper>
					<egenskap typeId="10223">
						<verdi>Nei</verdi>
					</egenskap>
					<egenskap typeId="6981">
						<verdi>Vann</verdi>
					</egenskap>
					<egenskap typeId="4549">
						<verdi>300</verdi>
					</egenskap>
					<egenskap typeId="7996">
						<verdi>Kommune</verdi>
					</egenskap>
					<egenskap typeId="4548">
						<verdi>300</verdi>
					</egenskap>
					<egenskap typeId="1941">
						<verdi>Nei</verdi>
					</egenskap>
					<egenskap typeId="6984">
						<verdi>Sirkulær</verdi>
					</egenskap>
					<egenskap typeId="1923">
						<verdi>Nei</verdi>
					</egenskap>
					<egenskap typeId="4562">
						<verdi>Masser, innløp</verdi>
					</egenskap>
					<egenskap typeId="6983">
						<verdi>Tre</verdi>
					</egenskap>
					<egenskap typeId="1939">
						<verdi>Åpent i grøft</verdi>
					</egenskap>
					<egenskap typeId="1940">
						<verdi>I skråning/terreng</verdi>
					</egenskap>
					<egenskap typeId="5899">
						<verdi>målemetode=96; nøyaktighet=10; synbarhet=1; målemetodeHøyde=96; nøyaktighetHøyde=10; LINESTRING(246872.33413844393 6815376.1102876663,246861.32369728261 6815378.5629214356)</verdi>
					</egenskap>
				</egenskaper>
				<assosiasjoner>
					<assosiasjon typeId="221093">
						<tempId>-1255</tempId>
					</assosiasjon>
				</assosiasjoner>
				<lokasjon>
					<punkt lenkeId="1003412" posisjon="0.27279477000209285"/>
				</lokasjon>
			</vegObjekt>
			<vegObjekt typeId="79" tempId="-1256">
				<egenskaper>
					<egenskap typeId="1941">
						<verdi>Nei</verdi>
					</egenskap>
					<egenskap typeId="6981">
						<verdi>Vann</verdi>
					</egenskap>
					<egenskap typeId="10223">
						<verdi>Nei</verdi>
					</egenskap>
					<egenskap typeId="6984">
						<verdi>Sirkulær</verdi>
					</egenskap>
					<egenskap typeId="1923">
						<verdi>Nei</verdi>
					</egenskap>
					<egenskap typeId="4562">
						<verdi>Masser, innløp</verdi>
					</egenskap>
					<egenskap typeId="7996">
						<verdi>Kommune</verdi>
					</egenskap>
					<egenskap typeId="1939">
						<verdi>Åpent i grøft</verdi>
					</egenskap>
					<egenskap typeId="1940">
						<verdi>I skråning/terreng</verdi>
					</egenskap>
					<egenskap typeId="6983">
						<verdi>Tre</verdi>
					</egenskap>
					<egenskap typeId="5899">
						<verdi>målemetode=96; nøyaktighet=10; synbarhet=1; målemetodeHøyde=96; nøyaktighetHøyde=10; LINESTRING(246847.6084273562 6815528.522393439,246843.66433048787 6815525.0622301241)</verdi>
					</egenskap>
				</egenskaper>
				<assosiasjoner>
					<assosiasjon typeId="221093">
						<tempId>-1257</tempId>
					</assosiasjon>
				</assosiasjoner>
				<lokasjon>
					<punkt lenkeId="1003412" posisjon="0.31985249853277875"/>
				</lokasjon>
			</vegObjekt>
			<vegObjekt typeId="79" tempId="-1258">
				<egenskaper>
					<egenskap typeId="10223">
						<verdi>Nei</verdi>
					</egenskap>
					<egenskap typeId="6981">
						<verdi>Vann</verdi>
					</egenskap>
					<egenskap typeId="4549">
						<verdi>400</verdi>
					</egenskap>
					<egenskap typeId="7996">
						<verdi>Kommune</verdi>
					</egenskap>
					<egenskap typeId="4548">
						<verdi>700</verdi>
					</egenskap>
					<egenskap typeId="1941">
						<verdi>Nei</verdi>
					</egenskap>
					<egenskap typeId="6984">
						<verdi>Rektangulær</verdi>
					</egenskap>
					<egenskap typeId="1923">
						<verdi>Nei</verdi>
					</egenskap>
					<egenskap typeId="4562">
						<verdi>Masser, innløp</verdi>
					</egenskap>
					<egenskap typeId="6983">
						<verdi>Naturstein</verdi>
					</egenskap>
					<egenskap typeId="1939">
						<verdi>Åpent i grøft</verdi>
					</egenskap>
					<egenskap typeId="1940">
						<verdi>I skråning/terreng</verdi>
					</egenskap>
					<egenskap typeId="5899">
						<verdi>målemetode=96; nøyaktighet=10; synbarhet=1; målemetodeHøyde=96; nøyaktighetHøyde=10; LINESTRING(246887.90030659037 6815567.1086559361,246880.76123200054 6815554.9627003139)</verdi>
					</egenskap>
				</egenskaper>
				<assosiasjoner>
					<assosiasjon typeId="221093">
						<tempId>-1259</tempId>
					</assosiasjon>
				</assosiasjoner>
				<lokasjon>
					<punkt lenkeId="1003412" posisjon="0.37165540936279845"/>
				</lokasjon>
			</vegObjekt>
			<vegObjekt typeId="79" tempId="-1260">
				<egenskaper>
					<egenskap typeId="1941">
						<verdi>Nei</verdi>
					</egenskap>
					<egenskap typeId="6981">
						<verdi>Vann</verdi>
					</egenskap>
					<egenskap typeId="10223">
						<verdi>Nei</verdi>
					</egenskap>
					<egenskap typeId="6984">
						<verdi>Sirkulær</verdi>
					</egenskap>
					<egenskap typeId="1923">
						<verdi>Nei</verdi>
					</egenskap>
					<egenskap typeId="4562">
						<verdi>Masser, innløp</verdi>
					</egenskap>
					<egenskap typeId="7996">
						<verdi>Kommune</verdi>
					</egenskap>
					<egenskap typeId="1939">
						<verdi>Åpent i grøft</verdi>
					</egenskap>
					<egenskap typeId="1940">
						<verdi>I skråning/terreng</verdi>
					</egenskap>
					<egenskap typeId="6983">
						<verdi>Naturstein</verdi>
					</egenskap>
					<egenskap typeId="5899">
						<verdi>målemetode=96; nøyaktighet=10; synbarhet=1; målemetodeHøyde=96; nøyaktighetHøyde=10; LINESTRING(247004.35015894665 6815480.5958595853,246998.46034497209 6815479.0306537235)</verdi>
					</egenskap>
				</egenskaper>
				<assosiasjoner>
					<assosiasjon typeId="221093">
						<tempId>-1261</tempId>
					</assosiasjon>
				</assosiasjoner>
				<lokasjon>
					<punkt lenkeId="1003412" posisjon="0.4118189537411609"/>
				</lokasjon>
			</vegObjekt>
		</vegObjekter>
	</registrer>
</endringssett>
